omeku/__init__.py
omeku/dict.py
omeku/errors.py
omeku/http.py
omeku/omeku.py
omeku.py-1.1.0.dist-info/METADATA
omeku.py-1.1.0.dist-info/WHEEL
omeku.py-1.1.0.dist-info/top_level.txt
omeku.py-1.1.0.dist-info/RECORD
