Metadata-Version: 2.1
Name: omeku.py
Version: 1.1.0
Summary: A Python module that uses Omeku API
Home-page: https://github.com/jdev2005/omeku.py
Author: jdev2005
Author-email: UNKNOWN
License: MIT
Platform: UNKNOWN
Requires-Dist: requests
